{"sections":{"main":{"type":"main-page","disabled":true,"settings":{"breadcrumbs":false,"heading":true,"content":false}},"columns_block_CqqbQM":{"type":"columns-block","blocks":{"text_block_JmmfzK":{"type":"text_block","settings":{"enable_image":true,"enable_round":false,"fullwidth-image":false,"fullheight-image":true,"hide-image":false,"image":"shopify:\/\/shop_images\/Model_1x1_3_1.jpg","video":"","center-content":false,"title":"2 for $80","title_size":"large","title_tag":"h2","text":"","text_size":"small","button_label":"BOOK NOW","button_link":"https:\/\/support.skinkandy.com\/s\/booking-form?_gl=1*ovtoa1*_gcl_au*NDMyMDYzODQ1LjE3NDkxODMzNDg.","new_tab":true}},"text_block_BEHQYK":{"type":"text_block","settings":{"enable_image":true,"enable_round":false,"fullwidth-image":false,"fullheight-image":true,"hide-image":false,"image":"shopify:\/\/shop_images\/1x1_-_1_1.jpg","video":"","center-content":false,"title":"Buy 3, Get the 4th Free","title_size":"large","title_tag":"h2","text":"","text_size":"small","button_label":"Shop Now","button_link":"shopify:\/\/collections\/buy-3-get-one-free","new_tab":false}}},"block_order":["text_block_JmmfzK","text_block_BEHQYK"],"custom_css":[".grid__item.medium-up--one-half.text-.aos-init.aos-animate {text-align: center;}"],"settings":{"dark_mode":false,"class":"","title":"Welcome to {KandyClub!}","description":"<p>You’re officially part of Australia and New Zealand’s biggest piercing community.<\/p><p>At SkinKandy, we’re global leaders in safe, professional body piercings—with over 80 stores across Australia and New Zealand and a reputation built on trust, hygiene, and style. Whether you’re booking your first piercing or curating your next stack, you’re in expert hands.<\/p><p>Now that you're in, you’ve unlocked access to exclusive member perks!<br\/><\/p>","button_text":"","button_url":"","count":2,"bottom_space":true,"hide_line":true,"disable_grid":false,"two_column":false,"max_width":1704}},"custom_banner_3bAXUt":{"type":"custom-banner","blocks":{"title_VDkLBN":{"type":"title","settings":{"title":"OVER {80+} {LOCATIONS} ACROSS AUSTRALIA & NEW ZEALAND! ","size":"small","title_tag":"h2"}},"text_content_hBd8ww":{"type":"text-content","settings":{"content":"<p>With stores in major shopping centres across Queensland, New South Wales, Victoria, Western Australia, and South Australia—plus expanding locations in New Zealand—SkinKandy is the go-to destination for premium piercings and jewellery. <\/p>","size":"small"}},"title_zVLPar":{"type":"title","settings":{"title":"BOLD. BRAVE. CONFIDENT. FUN.","size":"large","title_tag":"h2"}},"text_content_7PEC7x":{"type":"text-content","settings":{"content":"<p>Your story, your piercing, your style.<br\/>Welcome to SkinKandy.<\/p>","size":"large"}},"button_TGnJHM":{"type":"button","settings":{"button_text":"Find a Store","button_url":"shopify:\/\/pages\/store-locations"}}},"block_order":["title_VDkLBN","text_content_hBd8ww","title_zVLPar","text_content_7PEC7x","button_TGnJHM"],"settings":{"desktop_image":"shopify:\/\/shop_images\/Model_-_Desktop.png","mobile_image":"shopify:\/\/shop_images\/Model_-_Mobile.png","bg_color":"#e9e5ed","left_image":false}}},"order":["main","columns_block_CqqbQM","custom_banner_3bAXUt"]}